[
	{"line": 0, "pass": 0, "pass_fail": 0, "npass": 0, "npass_fail": 0, "dstar": 0,"code": ":    0:Source:simple_single_diff_far.c"},
	{"line": 0, "pass": 0, "pass_fail": 0, "npass": 0, "npass_fail": 0, "dstar": 0,"code": ":    0:Graph:simple_single_diff_far.gcno"},
	{"line": 0, "pass": 0, "pass_fail": 0, "npass": 0, "npass_fail": 0, "dstar": 0,"code": ":    0:Data:simple_single_diff_far.gcda"},
	{"line": 0, "pass": 0, "pass_fail": 0, "npass": 0, "npass_fail": 0, "dstar": 0,"code": ":    0:Runs:1"},
	{"line": 0, "pass": 0, "pass_fail": 0, "npass": 0, "npass_fail": 0, "dstar": 0,"code": ":    0:Programs:1"},
	{"line": 1, "pass": 0, "pass_fail": 0, "npass": 0, "npass_fail": 0, "dstar": 0,"code": ":    1:#include <stdio.h>"},
	{"line": 2, "pass": 0, "pass_fail": 0, "npass": 0, "npass_fail": 0, "dstar": 0,"code": ":    2:#include <signal.h>"},
	{"line": 3, "pass": 0, "pass_fail": 0, "npass": 0, "npass_fail": 0, "dstar": 0,"code": ":    3:#include <time.h>"},
	{"line": 4, "pass": 0, "pass_fail": 0, "npass": 0, "npass_fail": 0, "dstar": 0,"code": ":    4:"},
	{"line": 5, "pass": 0, "pass_fail": 0, "npass": 0, "npass_fail": 0, "dstar": 0,"code": ":    5:void __gcov_flush();"},
	{"line": 6, "pass": 0, "pass_fail": 3044, "npass": 6957, "npass_fail": 0, "dstar": 5,"code": ":    6:void sighandler (int signo)"},
	{"line": 7, "pass": 0, "pass_fail": 0, "npass": 0, "npass_fail": 0, "dstar": 0,"code": ":    7:{"},
	{"line": 8, "pass": 0, "pass_fail": 3044, "npass": 6957, "npass_fail": 0, "dstar": 5,"code": ":    8:\t__gcov_flush();"},
	{"line": 9, "pass": 0, "pass_fail": 0, "npass": 6957, "npass_fail": 3044, "dstar": 0,"code": ":    9:}"},
	{"line": 10, "pass": 0, "pass_fail": 0, "npass": 0, "npass_fail": 0, "dstar": 0,"code": ":   10:int sigs[] = {SIGILL, SIGFPE, SIGABRT, SIGBUS, SIGSEGV, SIGHUP, SIGINT, SIGQUIT, SIGTERM};"},
	{"line": 11, "pass": 0, "pass_fail": 0, "npass": 0, "npass_fail": 0, "dstar": 0,"code": ":   11:"},
	{"line": 12, "pass": 0, "pass_fail": 965, "npass": 6957, "npass_fail": 2079, "dstar": 0.464165,"code": ":   12:int crash_func(int n)"},
	{"line": 13, "pass": 0, "pass_fail": 0, "npass": 0, "npass_fail": 0, "dstar": 0,"code": ":   13:{"},
	{"line": 14, "pass": 0, "pass_fail": 0, "npass": 0, "npass_fail": 0, "dstar": 0,"code": ":   14:\tchar str[10];"},
	{"line": 15, "pass": 0, "pass_fail": 965, "npass": 6957, "npass_fail": 2079, "dstar": 0.464165,"code": ":   15:\tmemset(str, 0, n); \/\/fault"},
	{"line": 16, "pass": 0, "pass_fail": 965, "npass": 6957, "npass_fail": 2079, "dstar": 0.464165,"code": ":   16:}"},
	{"line": 17, "pass": 0, "pass_fail": 0, "npass": 0, "npass_fail": 0, "dstar": 0,"code": ":   17:"},
	{"line": 18, "pass": 0, "pass_fail": 2079, "npass": 6957, "npass_fail": 965, "dstar": 2.1544,"code": ":   18:int crash_func2(int n)"},
	{"line": 19, "pass": 0, "pass_fail": 0, "npass": 0, "npass_fail": 0, "dstar": 0,"code": ":   19:{"},
	{"line": 20, "pass": 0, "pass_fail": 0, "npass": 0, "npass_fail": 0, "dstar": 0,"code": ":   20:\tchar str[10];"},
	{"line": 21, "pass": 0, "pass_fail": 2079, "npass": 6957, "npass_fail": 965, "dstar": 2.1544,"code": ":   21:\tmemset(str, 0, n); \/\/fault"},
	{"line": 22, "pass": 0, "pass_fail": 2079, "npass": 6957, "npass_fail": 965, "dstar": 2.1544,"code": ":   22:}"},
	{"line": 23, "pass": 0, "pass_fail": 0, "npass": 0, "npass_fail": 0, "dstar": 0,"code": ":   23:"},
	{"line": 24, "pass": 1204, "pass_fail": 965, "npass": 5753, "npass_fail": 2079, "dstar": 0.293938,"code": ":   24:int third_block(int c, int n)"},
	{"line": 25, "pass": 0, "pass_fail": 0, "npass": 0, "npass_fail": 0, "dstar": 0,"code": ":   25:{"},
	{"line": 26, "pass": 1204, "pass_fail": 965, "npass": 5753, "npass_fail": 2079, "dstar": 0.293938,"code": ":   26:\tif(c)"},
	{"line": 27, "pass": 0, "pass_fail": 965, "npass": 6957, "npass_fail": 2079, "dstar": 0.464165,"code": ":   27:\t\tcrash_func(n);"},
	{"line": 28, "pass": 0, "pass_fail": 0, "npass": 0, "npass_fail": 0, "dstar": 0,"code": ":   28:\telse"},
	{"line": 29, "pass": 1204, "pass_fail": 0, "npass": 5753, "npass_fail": 3044, "dstar": 0,"code": ":   29:\t\tprintf(\"normal 3 end\\n\");"},
	{"line": 30, "pass": 1204, "pass_fail": 0, "npass": 5753, "npass_fail": 3044, "dstar": 0,"code": ":   30:}"},
	{"line": 31, "pass": 0, "pass_fail": 0, "npass": 0, "npass_fail": 0, "dstar": 0,"code": ":   31:"},
	{"line": 32, "pass": 1204, "pass_fail": 3044, "npass": 5753, "npass_fail": 0, "dstar": 2.52824,"code": ":   32:int second_block(int b, int n)"},
	{"line": 33, "pass": 0, "pass_fail": 0, "npass": 0, "npass_fail": 0, "dstar": 0,"code": ":   33:{"},
	{"line": 34, "pass": 1204, "pass_fail": 3044, "npass": 5753, "npass_fail": 0, "dstar": 2.52824,"code": ":   34:\tif (b)"},
	{"line": 35, "pass": 0, "pass_fail": 0, "npass": 0, "npass_fail": 0, "dstar": 0,"code": ":   35:\t{"},
	{"line": 36, "pass": 1204, "pass_fail": 965, "npass": 5753, "npass_fail": 2079, "dstar": 0.293938,"code": ":   36:\t\tint c = rand()%2;"},
	{"line": 37, "pass": 1204, "pass_fail": 965, "npass": 5753, "npass_fail": 2079, "dstar": 0.293938,"code": ":   37:\t\tthird_block(c, n);"},
	{"line": 38, "pass": 0, "pass_fail": 0, "npass": 0, "npass_fail": 0, "dstar": 0,"code": ":   38:\t}"},
	{"line": 39, "pass": 0, "pass_fail": 0, "npass": 0, "npass_fail": 0, "dstar": 0,"code": ":   39:\telse"},
	{"line": 40, "pass": 0, "pass_fail": 2079, "npass": 6957, "npass_fail": 965, "dstar": 2.1544,"code": ":   40:\t\tcrash_func2(n);"},
	{"line": 41, "pass": 0, "pass_fail": 0, "npass": 0, "npass_fail": 0, "dstar": 0,"code": ":   41:\t\t\/\/printf (\"normal 2 end\\n\");"},
	{"line": 42, "pass": 1204, "pass_fail": 0, "npass": 5753, "npass_fail": 3044, "dstar": 0,"code": ":   42:}"},
	{"line": 43, "pass": 0, "pass_fail": 0, "npass": 0, "npass_fail": 0, "dstar": 0,"code": ":   43:"},
	{"line": 44, "pass": 6957, "pass_fail": 3044, "npass": 0, "npass_fail": 0, "dstar": 0.437545,"code": ":   44:int first_block(int a, int n)"},
	{"line": 45, "pass": 0, "pass_fail": 0, "npass": 0, "npass_fail": 0, "dstar": 0,"code": ":   45:{"},
	{"line": 46, "pass": 6957, "pass_fail": 3044, "npass": 0, "npass_fail": 0, "dstar": 0.437545,"code": ":   46:\tif (a)"},
	{"line": 47, "pass": 0, "pass_fail": 0, "npass": 0, "npass_fail": 0, "dstar": 0,"code": ":   47:\t{"},
	{"line": 48, "pass": 1204, "pass_fail": 3044, "npass": 5753, "npass_fail": 0, "dstar": 2.52824,"code": ":   48:\t\tint b = rand()%2;"},
	{"line": 49, "pass": 1204, "pass_fail": 3044, "npass": 5753, "npass_fail": 0, "dstar": 2.52824,"code": ":   49:\t\tsecond_block(b, n);"},
	{"line": 50, "pass": 0, "pass_fail": 0, "npass": 0, "npass_fail": 0, "dstar": 0,"code": ":   50:\t}"},
	{"line": 51, "pass": 0, "pass_fail": 0, "npass": 0, "npass_fail": 0, "dstar": 0,"code": ":   51:\telse"},
	{"line": 52, "pass": 5753, "pass_fail": 0, "npass": 1204, "npass_fail": 3044, "dstar": 0,"code": ":   52:\t\tprintf (\"normal 1 end\\n\");"},
	{"line": 53, "pass": 6957, "pass_fail": 0, "npass": 0, "npass_fail": 3044, "dstar": 0,"code": ":   53:}"},
	{"line": 54, "pass": 0, "pass_fail": 0, "npass": 0, "npass_fail": 0, "dstar": 0,"code": ":   54:"},
	{"line": 55, "pass": 0, "pass_fail": 0, "npass": 0, "npass_fail": 0, "dstar": 0,"code": ":   55:"},
	{"line": 56, "pass": 6957, "pass_fail": 3044, "npass": 0, "npass_fail": 0, "dstar": 0.437545,"code": ":   56:int main (int argc, char** argv)"},
	{"line": 57, "pass": 0, "pass_fail": 0, "npass": 0, "npass_fail": 0, "dstar": 0,"code": ":   57:{"},
	{"line": 58, "pass": 0, "pass_fail": 0, "npass": 0, "npass_fail": 0, "dstar": 0,"code": ":   58:\tint sigcnt;"},
	{"line": 59, "pass": 0, "pass_fail": 0, "npass": 0, "npass_fail": 0, "dstar": 0,"code": ":   59:\tstruct sigaction sa;"},
	{"line": 60, "pass": 6957, "pass_fail": 3044, "npass": 0, "npass_fail": 0, "dstar": 0.437545,"code": ":   60:\tsa.sa_handler = sighandler;"},
	{"line": 61, "pass": 6957, "pass_fail": 3044, "npass": 0, "npass_fail": 0, "dstar": 0.437545,"code": ":   61:\tsigemptyset (&sa.sa_mask);"},
	{"line": 62, "pass": 6957, "pass_fail": 3044, "npass": 0, "npass_fail": 0, "dstar": 0.437545,"code": ":   62:\tsa.sa_flags = SA_RESETHAND;"},
	{"line": 63, "pass": 69570, "pass_fail": 30440, "npass": 0, "npass_fail": 0, "dstar": 0.437545,"code": ":   63:\tfor (sigcnt=0; sigcnt<sizeof(sigs)\/sizeof(sigs[0]); sigcnt++)"},
	{"line": 64, "pass": 62613, "pass_fail": 27396, "npass": 0, "npass_fail": 0, "dstar": 0.437545,"code": ":   64:\t\tif (sigaction (sigs[sigcnt], &sa, NULL) == -1)"},
	{"line": 65, "pass": 0, "pass_fail": 0, "npass": 6957, "npass_fail": 3044, "dstar": 0,"code": ":   65:\t\t\tprintf(\"%d error\\n\", sigs[sigcnt]);"},
	{"line": 66, "pass": 0, "pass_fail": 0, "npass": 0, "npass_fail": 0, "dstar": 0,"code": ":   66:"},
	{"line": 67, "pass": 6957, "pass_fail": 3044, "npass": 0, "npass_fail": 0, "dstar": 0.437545,"code": ":   67:\tsrand(time(NULL));"},
	{"line": 68, "pass": 6957, "pass_fail": 3044, "npass": 0, "npass_fail": 0, "dstar": 0.437545,"code": ":   68:\tint n = -1; \/\/fault"},
	{"line": 69, "pass": 6957, "pass_fail": 3044, "npass": 0, "npass_fail": 0, "dstar": 0.437545,"code": ":   69:\tint a = rand()%2;"},
	{"line": 70, "pass": 6957, "pass_fail": 3044, "npass": 0, "npass_fail": 0, "dstar": 0.437545,"code": ":   70:\tfirst_block(a, n);"},
	{"line": 71, "pass": 6957, "pass_fail": 0, "npass": 0, "npass_fail": 3044, "dstar": 0,"code": ":   71:\treturn 0;"},
	{"line": 72, "pass": 0, "pass_fail": 0, "npass": 0, "npass_fail": 0, "dstar": 0,"code": ":   72:}"}
]